odoo/addons/purchase_order_analytic_search/README.rst
odoo/addons/purchase_order_analytic_search/__init__.py
odoo/addons/purchase_order_analytic_search/__manifest__.py
odoo/addons/purchase_order_analytic_search/i18n/purchase_order_analytic_search.pot
odoo/addons/purchase_order_analytic_search/i18n/sl.po
odoo/addons/purchase_order_analytic_search/models/__init__.py
odoo/addons/purchase_order_analytic_search/models/purchase_order.py
odoo/addons/purchase_order_analytic_search/readme/CONTRIBUTORS.rst
odoo/addons/purchase_order_analytic_search/readme/DESCRIPTION.rst
odoo/addons/purchase_order_analytic_search/readme/USAGE.rst
odoo/addons/purchase_order_analytic_search/static/description/icon.png
odoo/addons/purchase_order_analytic_search/static/description/index.html
odoo/addons/purchase_order_analytic_search/tests/__init__.py
odoo/addons/purchase_order_analytic_search/tests/test_analytic_search.py
odoo/addons/purchase_order_analytic_search/views/purchase_order_view.xml
odoo12_addon_purchase_order_analytic_search-12.0.1.0.0.99.dev8.dist-info/METADATA
odoo12_addon_purchase_order_analytic_search-12.0.1.0.0.99.dev8.dist-info/WHEEL
odoo12_addon_purchase_order_analytic_search-12.0.1.0.0.99.dev8.dist-info/top_level.txt
odoo12_addon_purchase_order_analytic_search-12.0.1.0.0.99.dev8.dist-info/RECORD
