Metadata-Version: 2.1
Name: odoo12-addon-purchase-order-analytic-search
Version: 12.0.1.0.0.99.dev8
Summary: Search purchase orders by analytic account. New menu entry in Purchasing to list purchase order lines.
Home-page: https://github.com/OCA/purchase-workflow
Author: Eficent, Camptocamp, Odoo Community Association (OCA)
Author-email: support@odoo-community.org
License: LGPL-3
Platform: UNKNOWN
Classifier: Programming Language :: Python
Classifier: Framework :: Odoo
Classifier: Framework :: Odoo :: 12.0
Classifier: License :: OSI Approved :: GNU Lesser General Public License v3 (LGPLv3)
Requires-Python: >=3.5
Requires-Dist: odoo <12.1dev,>=12.0a
